sequence_detector/Sequence_detector_1011.v
module SQ_1011(S_input, CLK, RST, D_output);
    input S_input, CLK, RST;
    output reg D_output;
    parameter Zero = 3'b000,
    One = 3'b001,
    OneZero = 3'b010,
    OneZeroOne = 3'b011,
    OneZeroOneOne = 3'b100;
    reg [2:0] current_state, next_state;

    always @(posedge CLK, posedge RST) begin
        if(RST == 1)
            current_state <= Zero;
        else
            current_state <= next_state;
    end

    always @(current_state, S_input) begin
        case (current_state)
            Zero:begin
                if(S_input == 0)
                    next_state = Zero;
                else
                    next_state = One;
            end
            One:begin
                if(S_input == 0)
                    next_state = OneZero;
                else
                    next_state = One;
            end
            OneZero:begin
                if(S_input == 0)
                    next_state = Zero;
                else
                    next_state = OneZeroOne;
            end
            OneZeroOne:begin
                if(S_input == 0)
                    next_state = OneZero;
                else
                    next_state = OneZeroOneOne;
            end
            OneZeroOneOne:begin
                if(S_input == 0)
                    next_state = OneZero;
                else
                    next_state = One;
            end
            default: next_state = Zero;
        endcase
    end

    always @(current_state) begin
        case (current_state)
            Zero: D_output = 0;
            One: D_output = 0;
            OneZero: D_output = 0; 
            OneZeroOne: D_output = 0; 
            OneZeroOneOne: D_output = 1;  
            default: D_output = 0;
        endcase
    end

    initial begin
        $monitor($time, " current_state = %b, next_state = %b", current_state, next_state);
    end
endmodule

sequence_detector/Sequence_detector_1011_tb.v
`timescale 1ns / 1ps
// fpga4student.com: FPGA projects, Verilog projects, VHDL projects
// Verilog project: Verilog code for Sequence Detector using Moore FSM
// Verilog Testbench for Sequence Detector using Moore FSM 
module Sequence_detector_1011_tb;

 // Inputs
 reg sequence_in;
 reg clock;
 reg reset;

 // Outputs
 wire detector_out;

 // Instantiate the Sequence Detector using Moore FSM
 SQ_1011 uut (
  .S_input(sequence_in), 
  .CLK(clock), 
  .RST(reset), 
  .D_output(detector_out)
 );
 initial begin
 clock = 0;
 forever #5 clock = ~clock;
 end 
 initial begin
    $dumpfile("dump.vcd");
    $dumpvars(1, Sequence_detector_1011_tb);
  // Initialize Inputs
  sequence_in = 0;
  reset = 1;
  // Wait 100 ns for global reset to finish
  #40;
      reset = 0;
  #30;
  sequence_in = 1;
  #10;
  sequence_in = 0;
  #10;
  sequence_in = 1; 
  #20;
  sequence_in = 0; 
  #20;
  sequence_in = 1; 
  #20;
  sequence_in = 1;  
  // Add stimulus here
  $monitor($time ," y = %b",$time, detector_out);
  #10 $finish;

 end
      
endmodule

sequence_detector/dump.vcd
$date
	Fri Nov 25 17:27:23 2022
$end
$version
	Icarus Verilog
$end
$timescale
	1ps
$end
$scope module Sequence_detector_1011_tb $end
$var wire 1 ! detector_out $end
$var reg 1 " clock $end
$var reg 1 # reset $end
$var reg 1 $ sequence_in $end
$upscope $end
$enddefinitions $end
$comment Show the parameter values. $end
$dumpall
$end
#0
$dumpvars
0$
1#
0"
0!
$end
#5000
1"
#10000
0"
#15000
1"
#20000
0"
#25000
1"
#30000
0"
#35000
1"
#40000
0"
0#
#45000
1"
#50000
0"
#55000
1"
#60000
0"
#65000
1"
#70000
0"
1$
#75000
1"
#80000
0"
0$
#85000
1"
#90000
0"
1$
#95000
1"
#100000
0"
#105000
1!
1"
#110000
0"
0$
#115000
0!
1"
#120000
0"
#125000
1"
#130000
0"
1$
